book_package_svk/__init__.py
book_package_svk/book.py
book_package_svk-0.0.2.dist-info/LICENSE
book_package_svk-0.0.2.dist-info/METADATA
book_package_svk-0.0.2.dist-info/WHEEL
book_package_svk-0.0.2.dist-info/top_level.txt
book_package_svk-0.0.2.dist-info/RECORD
